{ "_id": "audp2114", "co_autor": "2114", "nome": "Joachim Du Bellay   ", "total_obras": 3, "tipo": "autor", "record": [{ "co_obra": 7278, "titulo": "Oeuvres Poétiques", "co_categoria": "cadp2", "co_autor": "audp2114", "co_idioma": "iddp10", "nome_idioma": "Francês", "nome_categoria": "Literatura", "nome_autor": "Joachim Du Bellay   ", "formato": "pdf", "co_midia": 2, "tipo": "obra"}, { "co_obra": 7281, "titulo": "Recueils Romains", "co_categoria": "cadp2", "co_autor": "audp2114", "co_idioma": "iddp10", "nome_idioma": "Francês", "nome_categoria": "Literatura", "nome_autor": "Joachim Du Bellay   ", "formato": "pdf", "co_midia": 2, "tipo": "obra"}, { "co_obra": 84347, "titulo": "Les Antiquités de Rome", "co_categoria": "cadp2", "co_autor": "audp2114", "co_idioma": "iddp10", "nome_idioma": "Francês", "nome_categoria": "Literatura", "nome_autor": "Joachim Du Bellay   ", "formato": "pdf", "co_midia": 2, "tipo": "obra"}]}
