{ "_id": "audp2096", "co_autor": "2096", "nome": "William Blake   ", "total_obras": 24, "tipo": "autor", "record": [{ "co_obra": 7079, "titulo": "A Poison Tree", "co_categoria": "cadp2", "co_autor": "audp2096", "co_idioma": "iddp2", "nome_idioma": "Inglês", "nome_categoria": "Literatura", "nome_autor": "William Blake   ", "formato": "pdf", "tipo": "obra"}, { "co_obra": 7080, "titulo": "And Did Those Feet in Ancient Time", "co_categoria": "cadp2", "co_autor": "audp2096", "co_idioma": "iddp2", "nome_idioma": "Inglês", "nome_categoria": "Literatura", "nome_autor": "William Blake   ", "formato": "pdf", "tipo": "obra"}, { "co_obra": 7081, "titulo": "Auguries of Innocence", "co_categoria": "cadp2", "co_autor": "audp2096", "co_idioma": "iddp2", "nome_idioma": "Inglês", "nome_categoria": "Literatura", "nome_autor": "William Blake   ", "formato": "pdf", "tipo": "obra"}, { "co_obra": 7082, "titulo": "Holy Thursday", "co_categoria": "cadp2", "co_autor": "audp2096", "co_idioma": "iddp2", "nome_idioma": "Inglês", "nome_categoria": "Literatura", "nome_autor": "William Blake   ", "formato": "pdf", "tipo": "obra"}, { "co_obra": 7083, "titulo": "Infant Sorrow", "co_categoria": "cadp2", "co_autor": "audp2096", "co_idioma": "iddp2", "nome_idioma": "Inglês", "nome_categoria": "Literatura", "nome_autor": "William Blake   ", "formato": "pdf", "tipo": "obra"}, { "co_obra": 7084, "titulo": "Introduction to Songs of Innocence", "co_categoria": "cadp2", "co_autor": "audp2096", "co_idioma": "iddp2", "nome_idioma": "Inglês", "nome_categoria": "Literatura", "nome_autor": "William Blake   ", "formato": "pdf", "tipo": "obra"}, { "co_obra": 7085, "titulo": "Love's Secret", "co_categoria": "cadp2", "co_autor": "audp2096", "co_idioma": "iddp2", "nome_idioma": "Inglês", "nome_categoria": "Literatura", "nome_autor": "William Blake   ", "formato": "pdf", "tipo": "obra"}, { "co_obra": 7086, "titulo": "Songs of Experience-My Pretty Rose-Tree", "co_categoria": "cadp2", "co_autor": "audp2096", "co_idioma": "iddp2", "nome_idioma": "Inglês", "nome_categoria": "Literatura", "nome_autor": "William Blake   ", "formato": "pdf", "tipo": "obra"}, { "co_obra": 7087, "titulo": "Songs of Experience-The Fly", "co_categoria": "cadp2", "co_autor": "audp2096", "co_idioma": "iddp2", "nome_idioma": "Inglês", "nome_categoria": "Literatura", "nome_autor": "William Blake   ", "formato": "pdf", "tipo": "obra"}, { "co_obra": 7088, "titulo": "Songs of Experience-The Sunflower", "co_categoria": "cadp2", "co_autor": "audp2096", "co_idioma": "iddp2", "nome_idioma": "Inglês", "nome_categoria": "Literatura", "nome_autor": "William Blake   ", "formato": "pdf", "tipo": "obra"}, { "co_obra": 7089, "titulo": "Songs of Innocence-Night", "co_categoria": "cadp2", "co_autor": "audp2096", "co_idioma": "iddp2", "nome_idioma": "Inglês", "nome_categoria": "Literatura", "nome_autor": "William Blake   ", "formato": "pdf", "tipo": "obra"}, { "co_obra": 7090, "titulo": "Songs of Innocence-The Chimney Sweeper", "co_categoria": "cadp2", "co_autor": "audp2096", "co_idioma": "iddp2", "nome_idioma": "Inglês", "nome_categoria": "Literatura", "nome_autor": "William Blake   ", "formato": "pdf", "tipo": "obra"}, { "co_obra": 7091, "titulo": "Songs of Innocence-The Little Black Boy", "co_categoria": "cadp2", "co_autor": "audp2096", "co_idioma": "iddp2", "nome_idioma": "Inglês", "nome_categoria": "Literatura", "nome_autor": "William Blake   ", "formato": "pdf", "tipo": "obra"}, { "co_obra": 7092, "titulo": "Songs of Innocence-The Schoolboy", "co_categoria": "cadp2", "co_autor": "audp2096", "co_idioma": "iddp2", "nome_idioma": "Inglês", "nome_categoria": "Literatura", "nome_autor": "William Blake   ", "formato": "pdf", "tipo": "obra"}, { "co_obra": 7093, "titulo": "Songs of Innocence-The Shepherd", "co_categoria": "cadp2", "co_autor": "audp2096", "co_idioma": "iddp2", "nome_idioma": "Inglês", "nome_categoria": "Literatura", "nome_autor": "William Blake   ", "formato": "pdf", "tipo": "obra"}, { "co_obra": 7094, "titulo": "The Chimney Sweeper", "co_categoria": "cadp2", "co_autor": "audp2096", "co_idioma": "iddp2", "nome_idioma": "Inglês", "nome_categoria": "Literatura", "nome_autor": "William Blake   ", "formato": "pdf", "tipo": "obra"}, { "co_obra": 7095, "titulo": "The Clod and the Pebble", "co_categoria": "cadp2", "co_autor": "audp2096", "co_idioma": "iddp2", "nome_idioma": "Inglês", "nome_categoria": "Literatura", "nome_autor": "William Blake   ", "formato": "pdf", "tipo": "obra"}, { "co_obra": 7096, "titulo": "The Garden of Love", "co_categoria": "cadp2", "co_autor": "audp2096", "co_idioma": "iddp2", "nome_idioma": "Inglês", "nome_categoria": "Literatura", "nome_autor": "William Blake   ", "formato": "pdf", "tipo": "obra"}, { "co_obra": 7097, "titulo": "The Lamb", "co_categoria": "cadp2", "co_autor": "audp2096", "co_idioma": "iddp2", "nome_idioma": "Inglês", "nome_categoria": "Literatura", "nome_autor": "William Blake   ", "formato": "pdf", "tipo": "obra"}, { "co_obra": 7098, "titulo": "The Land of Dreams", "co_categoria": "cadp2", "co_autor": "audp2096", "co_idioma": "iddp2", "nome_idioma": "Inglês", "nome_categoria": "Literatura", "nome_autor": "William Blake   ", "formato": "pdf", "tipo": "obra"}, { "co_obra": 7099, "titulo": "The Sick Rose", "co_categoria": "cadp2", "co_autor": "audp2096", "co_idioma": "iddp2", "nome_idioma": "Inglês", "nome_categoria": "Literatura", "nome_autor": "William Blake   ", "formato": "pdf", "tipo": "obra"}, { "co_obra": 7100, "titulo": "The Tiger", "co_categoria": "cadp2", "co_autor": "audp2096", "co_idioma": "iddp2", "nome_idioma": "Inglês", "nome_categoria": "Literatura", "nome_autor": "William Blake   ", "formato": "pdf", "tipo": "obra"}, { "co_obra": 11859, "titulo": "Poems", "co_categoria": "cadp2", "co_autor": "audp2096", "co_idioma": "iddp2", "nome_idioma": "Inglês", "nome_categoria": "Literatura", "nome_autor": "William Blake   ", "formato": "pdf", "tipo": "obra"}, { "co_obra": 18202, "titulo": "Songs of innocence and songs of experience", "co_categoria": "cadp2", "co_autor": "audp2096", "co_idioma": "iddp2", "nome_idioma": "Inglês", "nome_categoria": "Literatura", "nome_autor": "William Blake   ", "formato": "pdf", "tipo": "obra"}]}
