{ "_id": "audp30292", "co_autor": "30292", "nome": "Adolfo Coelho   ", "total_obras": 4, "tipo": "autor", "record": [{ "co_obra": 81601, "titulo": "Bela-Menina", "co_categoria": "cadp2", "co_autor": "audp30292", "co_idioma": "iddp1", "nome_idioma": "Português", "nome_categoria": "Literatura", "nome_autor": "Adolfo Coelho   ", "tipo": "obra"}, { "co_obra": 81603, "titulo": "Comadre Morte", "co_categoria": "cadp2", "co_autor": "audp30292", "co_idioma": "iddp1", "nome_idioma": "Português", "nome_categoria": "Literatura", "nome_autor": "Adolfo Coelho   ", "tipo": "obra"}, { "co_obra": 81608, "titulo": "O Príncipe Sapo", "co_categoria": "cadp2", "co_autor": "audp30292", "co_idioma": "iddp1", "nome_idioma": "Português", "nome_categoria": "Literatura", "nome_autor": "Adolfo Coelho   ", "tipo": "obra"}, { "co_obra": 81609, "titulo": "História do compadre rico e do compadre pobre", "co_categoria": "cadp2", "co_autor": "audp30292", "co_idioma": "iddp1", "nome_idioma": "Português", "nome_categoria": "Literatura", "nome_autor": "Adolfo Coelho   ", "tipo": "obra"}]}
