{ "_id": "audp16509", "co_autor": "16509", "nome": "Samuel de Champlain   ", "total_obras": 3, "tipo": "autor", "record": [{ "co_obra": 37749, "titulo": "Voyages of Samuel de Champlain, volume 1", "co_categoria": "cadp41", "co_autor": "audp16509", "co_idioma": "iddp2", "nome_idioma": "Inglês", "nome_categoria": "História", "nome_autor": "Samuel de Champlain   ", "formato": "pdf", "tipo": "obra"}, { "co_obra": 37910, "titulo": "Voyages of Samuel de Champlain Vol. 2", "co_categoria": "cadp41", "co_autor": "audp16509", "co_idioma": "iddp2", "nome_idioma": "Inglês", "nome_categoria": "História", "nome_autor": "Samuel de Champlain   ", "formato": "pdf", "tipo": "obra"}, { "co_obra": 38000, "titulo": "Voyages of Samuel de Champlain V3", "co_categoria": "cadp41", "co_autor": "audp16509", "co_idioma": "iddp2", "nome_idioma": "Inglês", "nome_categoria": "História", "nome_autor": "Samuel de Champlain   ", "formato": "pdf", "tipo": "obra"}]}
