{ "_id": "audp4517", "co_autor": "4517", "nome": "Rex Beach   ", "total_obras": 10, "tipo": "autor", "record": [{ "co_obra": 17593, "titulo": "Laughing Bill Hyde and Other Stories", "co_categoria": "cadp2", "co_autor": "audp4517", "co_idioma": "iddp2", "nome_idioma": "Inglês", "nome_categoria": "Literatura", "nome_autor": "Rex Beach   ", "formato": "pdf", "co_midia": 2, "tipo": "obra"}, { "co_obra": 23270, "titulo": "The Winds of Chance", "co_categoria": "cadp2", "co_autor": "audp4517", "co_idioma": "iddp2", "nome_idioma": "Inglês", "nome_categoria": "Literatura", "nome_autor": "Rex Beach   ", "formato": "pdf", "co_midia": 2, "tipo": "obra"}, { "co_obra": 23287, "titulo": "The Spoilers", "co_categoria": "cadp2", "co_autor": "audp4517", "co_idioma": "iddp2", "nome_idioma": "Inglês", "nome_categoria": "Literatura", "nome_autor": "Rex Beach   ", "formato": "pdf", "co_midia": 2, "tipo": "obra"}, { "co_obra": 23317, "titulo": "Heart of the Sunset", "co_categoria": "cadp2", "co_autor": "audp4517", "co_idioma": "iddp2", "nome_idioma": "Inglês", "nome_categoria": "Literatura", "nome_autor": "Rex Beach   ", "formato": "pdf", "co_midia": 2, "tipo": "obra"}, { "co_obra": 35998, "titulo": "The Ne'er-Do-Well", "co_categoria": "cadp2", "co_autor": "audp4517", "co_idioma": "iddp2", "nome_idioma": "Inglês", "nome_categoria": "Literatura", "nome_autor": "Rex Beach   ", "formato": "pdf", "co_midia": 2, "tipo": "obra"}, { "co_obra": 36295, "titulo": "The Silver Horde", "co_categoria": "cadp2", "co_autor": "audp4517", "co_idioma": "iddp2", "nome_idioma": "Inglês", "nome_categoria": "Literatura", "nome_autor": "Rex Beach   ", "formato": "pdf", "co_midia": 2, "tipo": "obra"}, { "co_obra": 36495, "titulo": "The Net", "co_categoria": "cadp2", "co_autor": "audp4517", "co_idioma": "iddp2", "nome_idioma": "Inglês", "nome_categoria": "Literatura", "nome_autor": "Rex Beach   ", "formato": "pdf", "co_midia": 2, "tipo": "obra"}, { "co_obra": 36965, "titulo": "Flowing Gold", "co_categoria": "cadp2", "co_autor": "audp4517", "co_idioma": "iddp2", "nome_idioma": "Inglês", "nome_categoria": "Literatura", "nome_autor": "Rex Beach   ", "formato": "pdf", "co_midia": 2, "tipo": "obra"}, { "co_obra": 37133, "titulo": "Going Some", "co_categoria": "cadp2", "co_autor": "audp4517", "co_idioma": "iddp2", "nome_idioma": "Inglês", "nome_categoria": "Literatura", "nome_autor": "Rex Beach   ", "formato": "pdf", "co_midia": 2, "tipo": "obra"}, { "co_obra": 81789, "titulo": "Pardners", "co_categoria": "cadp2", "co_autor": "audp4517", "co_idioma": "iddp2", "nome_idioma": "Inglês", "nome_categoria": "Literatura", "nome_autor": "Rex Beach   ", "formato": "pdf", "co_midia": 2, "tipo": "obra"}]}
