{ "_id": "audp3495", "co_autor": "3495", "nome": "Robert Michael Ballantyne   ", "total_obras": 5, "tipo": "autor", "record": [{ "co_obra": 12009, "titulo": "The Coral Island - A Tale of the Pacific Ocean", "co_categoria": "cadp2", "co_autor": "audp3495", "co_idioma": "iddp2", "nome_idioma": "Inglês", "nome_categoria": "Literatura", "nome_autor": "Robert Michael Ballantyne   ", "tipo": "obra"}, { "co_obra": 14402, "titulo": "The Dog Crusoe and His Master A Story of Adventure in the Western Prairies", "co_categoria": "cadp2", "co_autor": "audp3495", "co_idioma": "iddp2", "nome_idioma": "Inglês", "nome_categoria": "Literatura", "nome_autor": "Robert Michael Ballantyne   ", "tipo": "obra"}, { "co_obra": 18151, "titulo": "The world of ice", "co_categoria": "cadp2", "co_autor": "audp3495", "co_idioma": "iddp2", "nome_idioma": "Inglês", "nome_categoria": "Literatura", "nome_autor": "Robert Michael Ballantyne   ", "tipo": "obra"}, { "co_obra": 36473, "titulo": "The Young Fur Traders", "co_categoria": "cadp2", "co_autor": "audp3495", "co_idioma": "iddp2", "nome_idioma": "Inglês", "nome_categoria": "Literatura", "nome_autor": "Robert Michael Ballantyne   ", "tipo": "obra"}, { "co_obra": 38680, "titulo": "The Coral Island - A Tale Of The Pacific Ocean", "co_categoria": "cadp2", "co_autor": "audp3495", "co_idioma": "iddp2", "nome_idioma": "Inglês", "nome_categoria": "Literatura", "nome_autor": "Robert Michael Ballantyne   ", "tipo": "obra"}]}
