{ "_id": "cadp88", "pagina": 14, "total_paginas": 14, "co_categoria": "88", "nome": "Escola Brasil", "co_midia": 3, "total_obras": 272, "tipo": "categoria", "record": [{ "co_obra": 60635, "titulo": "Transporte escolar", "co_categoria": "cadp88", "co_autor": "audp1951", "co_idioma": "iddp1", "nome_idioma": "Português", "nome_autor": "Ministério da Educação   ", "nome_categoria": "Escola Brasil", "formato": "mp3", "gdrive": "", "co_midia": 3, "tipo": "obra"}, { "co_obra": 39034, "titulo": "Universalização da educação básica", "co_categoria": "cadp88", "co_autor": "audp1951", "co_idioma": "iddp5", "nome_idioma": "Não Aplicável", "nome_autor": "Ministério da Educação   ", "nome_categoria": "Escola Brasil", "formato": "mp3", "gdrive": "", "co_midia": 3, "tipo": "obra"}, { "co_obra": 60699, "titulo": "Valorização do professor. (out. 2007)", "co_categoria": "cadp88", "co_autor": "audp1951", "co_idioma": "iddp1", "nome_idioma": "Português", "nome_autor": "Ministério da Educação   ", "nome_categoria": "Escola Brasil", "formato": "mp3", "gdrive": "", "co_midia": 3, "tipo": "obra"}, { "co_obra": 60697, "titulo": "Valorização do professor: dia do professor. (out. 2007)", "co_categoria": "cadp88", "co_autor": "audp1951", "co_idioma": "iddp1", "nome_idioma": "Português", "nome_autor": "Ministério da Educação   ", "nome_categoria": "Escola Brasil", "formato": "mp3", "gdrive": "", "co_midia": 3, "tipo": "obra"}, { "co_obra": 46479, "titulo": "Valorizando o semi-árido", "co_categoria": "cadp88", "co_autor": "audp1951", "co_idioma": "iddp1", "nome_idioma": "Português", "nome_autor": "Ministério da Educação   ", "nome_categoria": "Escola Brasil", "formato": "mp3", "gdrive": "", "co_midia": 3, "tipo": "obra"}, { "co_obra": 39061, "titulo": "Verão com segurança", "co_categoria": "cadp88", "co_autor": "audp1951", "co_idioma": "iddp5", "nome_idioma": "Não Aplicável", "nome_autor": "Ministério da Educação   ", "nome_categoria": "Escola Brasil", "formato": "mp3", "gdrive": "", "co_midia": 3, "tipo": "obra"}, { "co_obra": 60704, "titulo": "Verdade ou lenda?", "co_categoria": "cadp88", "co_autor": "audp1951", "co_idioma": "iddp1", "nome_idioma": "Português", "nome_autor": "Ministério da Educação   ", "nome_categoria": "Escola Brasil", "formato": "mp3", "gdrive": "", "co_midia": 3, "tipo": "obra"}, { "co_obra": 39019, "titulo": "Violência", "co_categoria": "cadp88", "co_autor": "audp1951", "co_idioma": "iddp5", "nome_idioma": "Não Aplicável", "nome_autor": "Ministério da Educação   ", "nome_categoria": "Escola Brasil", "formato": "mp3", "gdrive": "", "co_midia": 3, "tipo": "obra"}, { "co_obra": 60703, "titulo": "Violência na escola", "co_categoria": "cadp88", "co_autor": "audp1951", "co_idioma": "iddp1", "nome_idioma": "Português", "nome_autor": "Ministério da Educação   ", "nome_categoria": "Escola Brasil", "formato": "mp3", "gdrive": "", "co_midia": 3, "tipo": "obra"}, { "co_obra": 46473, "titulo": "Voluntariado", "co_categoria": "cadp88", "co_autor": "audp1951", "co_idioma": "iddp1", "nome_idioma": "Português", "nome_autor": "Ministério da Educação   ", "nome_categoria": "Escola Brasil", "formato": "mp3", "gdrive": "", "co_midia": 3, "tipo": "obra"}]}
