{ "_id": "cadp2", "pagina": 422, "total_paginas": 769, "co_categoria": "2", "nome": "Literatura", "co_midia": 2, "total_obras": 15368, "tipo": "categoria", "record": [{ "co_obra": 44537, "titulo": "Occasional Poems (The Works of Whittier, Part 3, v. 4)", "co_categoria": "cadp2", "co_autor": "audp394", "co_idioma": "iddp2", "nome_idioma": "Inglês", "nome_autor": "John Greenleaf Whittier   ", "nome_categoria": "Literatura", "formato": "pdf", "co_midia": 2, "tipo": "obra"}, { "co_obra": 2097, "titulo": "Ocidentais", "co_categoria": "cadp2", "co_autor": "audp58", "co_idioma": "iddp1", "nome_idioma": "Português", "nome_autor": "Machado de Assis   ", "nome_categoria": "Literatura", "formato": "pdf", "co_midia": 2, "tipo": "obra"}, { "co_obra": 1925, "titulo": "Ocidentais", "co_categoria": "cadp2", "co_autor": "audp58", "co_idioma": "iddp1", "nome_idioma": "Português", "nome_autor": "Machado de Assis   ", "nome_categoria": "Literatura", "formato": "pdf", "co_midia": 2, "tipo": "obra"}, { "co_obra": 13476, "titulo": "October Vagabonds", "co_categoria": "cadp2", "co_autor": "audp271", "co_idioma": "iddp2", "nome_idioma": "Inglês", "nome_autor": "Richard Le Gallienne   ", "nome_categoria": "Literatura", "formato": "pdf", "co_midia": 2, "tipo": "obra"}, { "co_obra": 7495, "titulo": "Octogenário", "co_categoria": "cadp2", "co_autor": "audp2150", "co_idioma": "iddp1", "nome_idioma": "Português", "nome_autor": "Artur Azevedo   ", "nome_categoria": "Literatura", "formato": "pdf", "co_midia": 2, "tipo": "obra"}, { "co_obra": 79828, "titulo": "Odd Charges - Odd Craft, Part 13.", "co_categoria": "cadp2", "co_autor": "audp16397", "co_idioma": "iddp2", "nome_idioma": "Inglês", "nome_autor": "W. W. Jacobs   ", "nome_categoria": "Literatura", "formato": "pdf", "co_midia": 2, "tipo": "obra"}, { "co_obra": 79830, "titulo": "Odd Craft, Complete", "co_categoria": "cadp2", "co_autor": "audp16397", "co_idioma": "iddp2", "nome_idioma": "Inglês", "nome_autor": "W. W. Jacobs   ", "nome_categoria": "Literatura", "formato": "pdf", "co_midia": 2, "tipo": "obra"}, { "co_obra": 14213, "titulo": "Odd Man Out Sailor's Knots, Part 6.", "co_categoria": "cadp2", "co_autor": "audp16241", "co_idioma": "iddp2", "nome_idioma": "Inglês", "nome_autor": "William Wymark Jacobs   ", "nome_categoria": "Literatura", "formato": "pdf", "co_midia": 2, "tipo": "obra"}, { "co_obra": 7072, "titulo": "Odd Sayings Of Three Pilgrims", "co_categoria": "cadp2", "co_autor": "audp2095", "co_idioma": "iddp2", "nome_idioma": "Inglês", "nome_autor": "Honoré de Balzac   ", "nome_categoria": "Literatura", "formato": "pdf", "co_midia": 2, "tipo": "obra"}, { "co_obra": 86853, "titulo": "Ode ao dous de julho", "co_categoria": "cadp2", "co_autor": "audp12", "co_idioma": "iddp1", "nome_idioma": "Português", "nome_autor": "Antônio Frederico de Castro Alves   ", "nome_categoria": "Literatura", "formato": "pdf", "co_midia": 2, "tipo": "obra"}, { "co_obra": 7188, "titulo": "Ode on a Grecian Urn.", "co_categoria": "cadp2", "co_autor": "audp2111", "co_idioma": "iddp2", "nome_idioma": "Inglês", "nome_autor": "John Keats   ", "nome_categoria": "Literatura", "formato": "pdf", "co_midia": 2, "tipo": "obra"}, { "co_obra": 7189, "titulo": "Ode on Melancholy.", "co_categoria": "cadp2", "co_autor": "audp2111", "co_idioma": "iddp2", "nome_idioma": "Inglês", "nome_autor": "John Keats   ", "nome_categoria": "Literatura", "formato": "pdf", "co_midia": 2, "tipo": "obra"}, { "co_obra": 7190, "titulo": "Ode to a Nightingale.", "co_categoria": "cadp2", "co_autor": "audp2111", "co_idioma": "iddp2", "nome_idioma": "Inglês", "nome_autor": "John Keats   ", "nome_categoria": "Literatura", "formato": "pdf", "co_midia": 2, "tipo": "obra"}, { "co_obra": 7191, "titulo": "Ode to Autumn", "co_categoria": "cadp2", "co_autor": "audp2111", "co_idioma": "iddp2", "nome_idioma": "Inglês", "nome_autor": "John Keats   ", "nome_categoria": "Literatura", "formato": "pdf", "co_midia": 2, "tipo": "obra"}, { "co_obra": 7192, "titulo": "Ode to Psyche", "co_categoria": "cadp2", "co_autor": "audp2111", "co_idioma": "iddp2", "nome_idioma": "Inglês", "nome_autor": "John Keats   ", "nome_categoria": "Literatura", "formato": "pdf", "co_midia": 2, "tipo": "obra"}, { "co_obra": 38012, "titulo": "Oden", "co_categoria": "cadp2", "co_autor": "audp2890", "co_idioma": "iddp11", "nome_idioma": "Alemão", "nome_autor": "Gotthold Ephraim Lessing   ", "nome_categoria": "Literatura", "formato": "pdf", "co_midia": 2, "tipo": "obra"}, { "co_obra": 36076, "titulo": "Odes and Carmen Saeculare of Horace", "co_categoria": "cadp2", "co_autor": "audp2087", "co_idioma": "iddp2", "nome_idioma": "Inglês", "nome_autor": "Horacio   ", "nome_categoria": "Literatura", "formato": "pdf", "co_midia": 2, "tipo": "obra"}, { "co_obra": 43698, "titulo": "Odes and Epodes", "co_categoria": "cadp2", "co_autor": "audp2087", "co_idioma": "iddp9", "nome_idioma": "Latim", "nome_autor": "Horacio   ", "nome_categoria": "Literatura", "formato": "pdf", "co_midia": 2, "tipo": "obra"}, { "co_obra": 10504, "titulo": "Odes Funambulesques", "co_categoria": "cadp2", "co_autor": "audp2215", "co_idioma": "iddp10", "nome_idioma": "Francês", "nome_autor": "Théodore de Banville   ", "nome_categoria": "Literatura", "formato": "pdf", "co_midia": 2, "tipo": "obra"}, { "co_obra": 86325, "titulo": "Odes politiques", "co_categoria": "cadp2", "co_autor": "audp2588", "co_idioma": "iddp10", "nome_idioma": "Francês", "nome_autor": "Alphonse de Lamartine   ", "nome_categoria": "Literatura", "formato": "pdf", "co_midia": 2, "tipo": "obra"}]}
