{ "_id": "cadp44", "pagina": 45, "total_paginas": 158, "co_categoria": "44", "nome": "Educação", "co_midia": 2, "total_obras": 3148, "tipo": "categoria", "record": [{ "co_obra": 17994, "titulo": "Em Aberto, Brasília, ano 11, n° 56, out./dez. 1992", "co_categoria": "cadp44", "co_autor": "audp1951", "co_idioma": "iddp1", "nome_idioma": "Português", "nome_autor": "Ministério da Educação   ", "nome_categoria": "Educação", "tipo": "obra"}, { "co_obra": 17993, "titulo": "Em Aberto, Brasilia, ano 11, nº 55, jul./set. 1992", "co_categoria": "cadp44", "co_autor": "audp1951", "co_idioma": "iddp1", "nome_idioma": "Português", "nome_autor": "Ministério da Educação   ", "nome_categoria": "Educação", "tipo": "obra"}, { "co_obra": 17992, "titulo": "Em Aberto, Brasília, ano 12, n.54, abr./jun. 1992", "co_categoria": "cadp44", "co_autor": "audp1951", "co_idioma": "iddp1", "nome_idioma": "Português", "nome_autor": "Ministério da Educação   ", "nome_categoria": "Educação", "tipo": "obra"}, { "co_obra": 17995, "titulo": "Em Aberto, Brasília, ano 12, n.57, jan./mar. 1993", "co_categoria": "cadp44", "co_autor": "audp1951", "co_idioma": "iddp1", "nome_idioma": "Português", "nome_autor": "Ministério da Educação   ", "nome_categoria": "Educação", "tipo": "obra"}, { "co_obra": 17996, "titulo": "Em Aberto, Brasília, ano 12. n.58, abr./jun. 1993", "co_categoria": "cadp44", "co_autor": "audp1951", "co_idioma": "iddp1", "nome_idioma": "Português", "nome_autor": "Ministério da Educação   ", "nome_categoria": "Educação", "tipo": "obra"}, { "co_obra": 17998, "titulo": "Em Aberto, Brasília, ano 13, n.60, out./dez. 1993", "co_categoria": "cadp44", "co_autor": "audp1951", "co_idioma": "iddp1", "nome_idioma": "Português", "nome_autor": "Ministério da Educação   ", "nome_categoria": "Educação", "tipo": "obra"}, { "co_obra": 18000, "titulo": "Em Aberto, Brasília, ano 14, n. 62, abr./jun. 1994", "co_categoria": "cadp44", "co_autor": "audp1951", "co_idioma": "iddp1", "nome_idioma": "Português", "nome_autor": "Ministério da Educação   ", "nome_categoria": "Educação", "tipo": "obra"}, { "co_obra": 17999, "titulo": "Em Aberto, Brasília, ano 14, n.61, jan./mar. 1994", "co_categoria": "cadp44", "co_autor": "audp1951", "co_idioma": "iddp1", "nome_idioma": "Português", "nome_autor": "Ministério da Educação   ", "nome_categoria": "Educação", "tipo": "obra"}, { "co_obra": 18001, "titulo": "Em Aberto, Brasília, ano 14, n.63 jul./set. 1994", "co_categoria": "cadp44", "co_autor": "audp1951", "co_idioma": "iddp1", "nome_idioma": "Português", "nome_autor": "Ministério da Educação   ", "nome_categoria": "Educação", "tipo": "obra"}, { "co_obra": 17963, "titulo": "Em Aberto, Brasília, ano 2, n. 12, jan. 1983", "co_categoria": "cadp44", "co_autor": "audp1951", "co_idioma": "iddp1", "nome_idioma": "Português", "nome_autor": "Ministério da Educação   ", "nome_categoria": "Educação", "tipo": "obra"}, { "co_obra": 17965, "titulo": "Em Aberto, Brasília, ano 2, n° 18, ago./nov. 1983", "co_categoria": "cadp44", "co_autor": "audp1951", "co_idioma": "iddp1", "nome_idioma": "Português", "nome_autor": "Ministério da Educação   ", "nome_categoria": "Educação", "tipo": "obra"}, { "co_obra": 17966, "titulo": "Em aberto, Brasília, ano 3, n. 21 ,mai./jun. 1984", "co_categoria": "cadp44", "co_autor": "audp1951", "co_idioma": "iddp1", "nome_idioma": "Português", "nome_autor": "Ministério da Educação   ", "nome_categoria": "Educação", "tipo": "obra"}, { "co_obra": 17968, "titulo": "Em Aberto, Brasília, ano 4, n. 28, out./dez. 1985", "co_categoria": "cadp44", "co_autor": "audp1951", "co_idioma": "iddp1", "nome_idioma": "Português", "nome_autor": "Ministério da Educação   ", "nome_categoria": "Educação", "tipo": "obra"}, { "co_obra": 17969, "titulo": "Em Aberto, Brasília, ano 5, n. 29, jan./mar. 1986", "co_categoria": "cadp44", "co_autor": "audp1951", "co_idioma": "iddp1", "nome_idioma": "Português", "nome_autor": "Ministério da Educação   ", "nome_categoria": "Educação", "tipo": "obra"}, { "co_obra": 17970, "titulo": "Em Aberto, Brasília, ano 5, n. 30, abr./jun. 1986", "co_categoria": "cadp44", "co_autor": "audp1951", "co_idioma": "iddp1", "nome_idioma": "Português", "nome_autor": "Ministério da Educação   ", "nome_categoria": "Educação", "tipo": "obra"}, { "co_obra": 17971, "titulo": "Em Aberto, Brasília, ano 5, n. 31, ago./set. 1986", "co_categoria": "cadp44", "co_autor": "audp1951", "co_idioma": "iddp1", "nome_idioma": "Português", "nome_autor": "Ministério da Educação   ", "nome_categoria": "Educação", "tipo": "obra"}, { "co_obra": 17972, "titulo": "Em Aberto, Brasília, ano 5, n. 32, out./dez. 1986", "co_categoria": "cadp44", "co_autor": "audp1951", "co_idioma": "iddp1", "nome_idioma": "Português", "nome_autor": "Ministério da Educação   ", "nome_categoria": "Educação", "tipo": "obra"}, { "co_obra": 17997, "titulo": "Em Aberto, Brasília, ano 5, n.31, ago./set. 1986", "co_categoria": "cadp44", "co_autor": "audp1951", "co_idioma": "iddp1", "nome_idioma": "Português", "nome_autor": "Ministério da Educação   ", "nome_categoria": "Educação", "tipo": "obra"}, { "co_obra": 17973, "titulo": "Em Aberto, Brasília, ano 6, n. 33, jan./mar. 1987", "co_categoria": "cadp44", "co_autor": "audp1951", "co_idioma": "iddp1", "nome_idioma": "Português", "nome_autor": "Ministério da Educação   ", "nome_categoria": "Educação", "tipo": "obra"}, { "co_obra": 17975, "titulo": "Em Aberto, Brasília, ano 6, n. 35, jul./set. 1987", "co_categoria": "cadp44", "co_autor": "audp1951", "co_idioma": "iddp1", "nome_idioma": "Português", "nome_autor": "Ministério da Educação   ", "nome_categoria": "Educação", "tipo": "obra"}]}
